maxmul_pkg/__init__.py
maxmul_pkg/mxmul.py
maxmul_pkg-1.0.1.dist-info/LICENSE
maxmul_pkg-1.0.1.dist-info/METADATA
maxmul_pkg-1.0.1.dist-info/WHEEL
maxmul_pkg-1.0.1.dist-info/top_level.txt
maxmul_pkg-1.0.1.dist-info/RECORD
