Metadata-Version: 2.1
Name: maxmul-pkg
Version: 1.0.1
Summary: an example
Home-page: UNKNOWN
Author: jobi
License: UNKNOWN
Platform: UNKNOWN
Classifier: Programming Language :: Python :: 3
Classifier: License :: OSI Approved :: MIT License
Classifier: Operating System :: OS Independent
